python_surveilclient-0.13.3.data/data/share/surveil.bash_completion
surveilclient/__init__.py
surveilclient/shell.py
surveilclient/exc.py
surveilclient/client.py
surveilclient/v2_0/__init__.py
surveilclient/v2_0/shell.py
surveilclient/v2_0/client.py
surveilclient/v2_0/actions/__init__.py
surveilclient/v2_0/actions/acknowledge.py
surveilclient/v2_0/actions/recheck.py
surveilclient/v2_0/actions/downtime.py
surveilclient/v2_0/config/hostgroups.py
surveilclient/v2_0/config/__init__.py
surveilclient/v2_0/config/notificationways.py
surveilclient/v2_0/config/servicegroups.py
surveilclient/v2_0/config/services.py
surveilclient/v2_0/config/contacts.py
surveilclient/v2_0/config/timeperiods.py
surveilclient/v2_0/config/hosts.py
surveilclient/v2_0/config/macromodulations.py
surveilclient/v2_0/config/checkmodulations.py
surveilclient/v2_0/config/contactgroups.py
surveilclient/v2_0/config/businessimpactmodulations.py
surveilclient/v2_0/config/commands.py
surveilclient/v2_0/config/realms.py
surveilclient/v2_0/status/__init__.py
surveilclient/v2_0/status/services.py
surveilclient/v2_0/status/hosts.py
surveilclient/v2_0/status/events.py
surveilclient/v2_0/status/metrics/__init__.py
surveilclient/v2_0/status/metrics/metrics.py
surveilclient/v1_0/__init__.py
surveilclient/v1_0/services.py
surveilclient/v1_0/shell.py
surveilclient/v1_0/hosts.py
surveilclient/v1_0/client.py
surveilclient/tests/__init__.py
surveilclient/tests/test_client.py
surveilclient/tests/test_shell.py
surveilclient/tests/v2_0/__init__.py
surveilclient/tests/v2_0/clienttest.py
surveilclient/tests/v2_0/actions/test_downtime.py
surveilclient/tests/v2_0/actions/__init__.py
surveilclient/tests/v2_0/actions/test_acknowledge.py
surveilclient/tests/v2_0/actions/test_recheck.py
surveilclient/tests/v2_0/config/test_services.py
surveilclient/tests/v2_0/config/__init__.py
surveilclient/tests/v2_0/config/test_realms.py
surveilclient/tests/v2_0/config/test_hostgroups.py
python_surveilclient-0.13.3.dist-info/WHEEL
python_surveilclient-0.13.3.dist-info/entry_points.txt
python_surveilclient-0.13.3.dist-info/pbr.json
python_surveilclient-0.13.3.dist-info/metadata.json
python_surveilclient-0.13.3.dist-info/RECORD
python_surveilclient-0.13.3.dist-info/DESCRIPTION.rst
python_surveilclient-0.13.3.dist-info/top_level.txt
python_surveilclient-0.13.3.dist-info/METADATA
