Metadata-Version: 2.0
Name: python-surveilclient
Version: 0.13.3
Summary: Surveil API Client Library
Home-page: UNKNOWN
Author: UNKNOWN
Author-email: UNKNOWN
License: UNKNOWN
Platform: UNKNOWN
Requires-Dist: oslo.serialization
Requires-Dist: prettytable
Requires-Dist: pbr
Requires-Dist: six
Requires-Dist: requests
Requires-Dist: mock
